<mbm>
  <entry id="0">
    <source>{f804}{0500}新宿{f804}{0000}でハンターが襲われる事件が多発している{f801}{f804}{0500}新宿二丁目{f804}{0000}に跋扈する{f804}{0500}ドアマース{f804}{0000}を駆逐してくれ{f801}…生存者によると ずいぶんと美しい悪魔らしいから{f801}惑わされぬよう気を引き締めるように{f801}{ffff}</source>
    <target>{f804}{0500}新宿{f804}{0000}でハンターが襲われる事件が多発している{f801}{f804}{0500}新宿二丁目{f804}{0000}に跋扈する{f804}{0500}ドアマース{f804}{0000}を駆逐してくれ{f801}…生存者によると ずいぶんと美しい悪魔らしいから{f801}惑わされぬよう気を引き締めるように{f801}{ffff}</target>
  </entry>
  <entry id="1">
    <source>納品クエストの説明文テンプレ 2回目{f801}クリア条件:{f801}{f872}{0100}を{f878}{0100}個持ってくる{f801}{f872}{0200}を{f878}{0200}個持ってくる{f801}{f872}{0300}を{f878}{0300}個持ってくる{f801}報酬:{f801}{f872}{0400} {f878}{0400}個{f801}{ffff}</source>
    <target>納品クエストの説明文テンプレ 2回目{f801}クリア条件:{f801}{f872}{0100}を{f878}{0100}個持ってくる{f801}{f872}{0200}を{f878}{0200}個持ってくる{f801}{f872}{0300}を{f878}{0300}個持ってくる{f801}報酬:{f801}{f872}{0400} {f878}{0400}個{f801}{ffff}</target>
  </entry>
  <entry id="10">
    <source>新宿を騒がす悪魔たちの討伐 ご苦労だった{f801}しかし悪魔に騙された悪魔が人を襲っていたとは…{f801}悪魔たちも一枚岩ではないようだな{f801}今回の事件…敵の敵は味方でなく やはり敵でしかない{f801}と言う事を改めて痛感させられる事件だったな{f801}悪魔には気を許さぬよう 気を引き締めて欲しい{f801}{ffff}</source>
    <target>新宿を騒がす悪魔たちの討伐 ご苦労だった{f801}しかし悪魔に騙された悪魔が人を襲っていたとは…{f801}悪魔たちも一枚岩ではないようだな{f801}今回の事件…敵の敵は味方でなく やはり敵でしかない{f801}と言う事を改めて痛感させられる事件だったな{f801}悪魔には気を許さぬよう 気を引き締めて欲しい{f801}{ffff}</target>
  </entry>
</mbm>