<mbm>
  <entry id="0">
    <source>通告各地的人外猎人。{f801}到东京各地找来{f804}{0500}规定量{f804}{0000}的{f804}{0500}食物{f804}{0000}。{f801}只要是能吃的东西就行。{f801}如果能找来超过规定量的食物,会支付追加报酬。{f801}全员,祈祷你们能为东京的居民尽一份力。{f801}{ffff}</source>
    <target>通告各地的人外猎人。{f801}到东京各地找来{f804}{0500}规定量{f804}{0000}的{f804}{0500}食物{f804}{0000}。{f801}只要是能吃的东西就行。{f801}如果能找来超过规定量的食物,会支付追加报酬。{f801}全员,祈祷你们能为东京的居民尽一份力。{f801}{ffff}</target>
  </entry>
  <entry id="1">
    <source>ダミー{f801}{ffff}</source>
    <target>ダミー{f801}{ffff}</target>
  </entry>
  <entry id="2">
    <source>给两位见习猎人的通知:{f801}日狩大哥决定要进行{f804}{0500}《战斗指导》{f804}{0000}。{f801}你们虽然还是见习,但也应该牢记战斗基础。{f801}日狩大哥是这样说的,Yeah man!{f801}去{f804}{0500}战斗几次{f804}{0000},掌握战斗的诀窍后{f801}再向日狩大哥报告。{f801}{ffff}</source>
    <target>给两位见习猎人的通知:{f801}日狩大哥决定要进行{f804}{0500}《战斗指导》{f804}{0000}。{f801}你们虽然还是见习,但也应该牢记战斗基础。{f801}日狩大哥是这样说的,Yeah man!{f801}去{f804}{0500}战斗几次{f804}{0000},掌握战斗的诀窍后{f801}再向日狩大哥报告。{f801}{ffff}</target>
  </entry>
  <entry id="3">
    <source>战斗这么多次的话,作为《战斗指导》应该足够了!{f801}快去日狩大哥那里吧。{f801}日狩大哥在{f804}{0500}喷泉前{f804}{0000}等着你们。{f801}{ffff}</source>
    <target>战斗这么多次的话,作为《战斗指导》应该足够了!{f801}快去日狩大哥那里吧。{f801}日狩大哥在{f804}{0500}喷泉前{f804}{0000}等着你们。{f801}{ffff}</target>
  </entry>
  <entry id="4">
    <source>给两位见习猎人的通知:{f801}《战斗指导》已经告一段落。{f801}接下来按照原来的计划,开始收集食物的任务。{f801}首先前往{f804}{0500}能够用作食物的恶魔出现的区域{f804}{0000},{f801}收集{f804}{0500}规定量的食物{f804}{0000}吧。{f801}{ffff}</source>
    <target>给两位见习猎人的通知:{f801}《战斗指导》已经告一段落。{f801}接下来按照原来的计划,开始收集食物的任务。{f801}首先前往{f804}{0500}能够用作食物的恶魔出现的区域{f804}{0000},{f801}收集{f804}{0500}规定量的食物{f804}{0000}吧。{f801}{ffff}</target>
  </entry>
  <entry id="5">
    <source>突然出现的恶魔《安杜马里》{f801}杀掉了日狩大哥和和学。{f801}要赶快把这件事告诉商会才行。{f801}去向{f804}{0500}锦糸町的人外猎人商会{f804}{0000}的{f804}{0500}店长报告吧{f804}{0000}。{f801}{ffff}</source>
    <target>突然出现的恶魔《安杜马里》{f801}杀掉了日狩大哥和学。{f801}要赶快把这件事告诉商会才行。{f801}去向{f804}{0500}锦糸町的人外猎人商会{f804}{0000}的{f804}{0500}店长报告吧{f804}{0000}。{f801}{ffff}</target>
  </entry>
</mbm>