<mbm>
  <entry id="1">
    <source>{f812}マルヲ{0000}{f81b}{4331}{3231}{3030}{3100}{0000}{0000}やりたい事をやって 自分を好きになる{f801}そんだけでヒトは十分ってワケぇ{f801}{f802}{f81b}{4331}{3231}{3030}{3200}{0000}{0000}ありのままの そのままの姿の力…{f801}感じてみなってことで!{f801}{ffff}</source>
    <target>{f812}マルヲ{0000}{f81b}{4331}{3231}{3030}{3100}{0000}{0000}やりたい事をやって 自分を好きになる{f801}そんだけでヒトは十分ってワケぇ{f801}{f802}{f81b}{4331}{3231}{3030}{3200}{0000}{0000}ありのままの そのままの姿の力…{f801}感じてみなってことで!{f801}{ffff}</target>
  </entry>
  <entry id="2">
    <source>{f812}マルヲ{0000}{f81b}{4331}{3231}{3030}{3300}{0000}{0000}あ〜〜…{f801}{f802}{f81b}{4331}{3231}{3030}{3400}{0000}{0000}だりィ{f801}{ffff}</source>
    <target>{f812}マルヲ{0000}{f81b}{4331}{3231}{3030}{3300}{0000}{0000}あ〜〜…{f801}{f802}{f81b}{4331}{3231}{3030}{3400}{0000}{0000}だりィ{f801}{ffff}</target>
  </entry>
</mbm>