<mbm>
  <entry id="0">
    <source>{f812}バロウズ{0000}{f87a}{0200}{f813}{0100}{0000}{be1a}{0600}サーチモード {f816}実行{f817}じっこう{f818}…{f801}ターゲット {f816}大陸間弾道{f817}たいりくかんだんどう{f818}ミサイル{f801}{ffff}</source>
    <target>{f812}バロウズ{0000}{f87a}{0200}{f813}{0100}{0000}{be1a}{0600}サーチモード {f816}実行{f817}じっこう{f818}…{f801}ターゲット {f816}大陸間弾道{f817}たいりくかんだんどう{f818}ミサイル{f801}{ffff}</target>
  </entry>
  <entry id="1">
    <source>{f812}バロウズ{0000}{f87a}{0200}サーチ{f816}完了{f817}かんりょう{f818}{f801}ミサイル{f816}到達{f817}とうたつ{f818}まで あと{f804}{0500}10ターン{f804}{0000}よ{f801}{f802}{f813}{0100}{0000}{5aab}{0400}{f843}{0000}{f816}様{f817}さま{f818}…{f801}{f802}{f816}東京{f817}とうきょう{f818}を{f816}守{f817}まも{f818}って…{f801}{ffff}</source>
    <target>{f812}バロウズ{0000}{f87a}{0200}サーチ{f816}完了{f817}かんりょう{f818}{f801}ミサイル{f816}到達{f817}とうたつ{f818}まで あと{f804}{0500}10ターン{f804}{0000}よ{f801}{f802}{f813}{0100}{0000}{5aab}{0400}{f843}{0000}{f816}様{f817}さま{f818}…{f801}{f802}{f816}東京{f817}とうきょう{f818}を{f816}守{f817}まも{f818}って…{f801}{ffff}</target>
  </entry>
  <entry id="2">
    <source>{f813}{0100}{0000}{5399}{0700}マサカドは{f801}{f816}戦{f817}たたか{f818}いの{f816}構{f817}かま{f818}えを{f816}取{f817}と{f818}った…{f801}{ffff}</source>
    <target>{f813}{0100}{0000}{5399}{0700}マサカドは{f801}{f816}戦{f817}たたか{f818}いの{f816}構{f817}かま{f818}えを{f816}取{f817}と{f818}った…{f801}{ffff}</target>
  </entry>
  <entry id="11">
    <source>マサカドの{f816}様子{f817}ようす{f818}が{f816}変{f817}か{f818}わった…{f801}{ffff}</source>
    <target>マサカドの{f816}様子{f817}ようす{f818}が{f816}変{f817}か{f818}わった…{f801}{ffff}</target>
  </entry>
  <entry id="12">
    <source>{f812}マサカド{0000}{f813}{0100}{0000}{5099}{0700}…{f816}悪{f817}わる{f818}い{f816}夢{f817}ゆめ{f818}を{f816}見{f817}み{f818}ていた{f801}{f802}{f816}我{f817}わ{f818}が{f816}体内{f817}たいない{f818}の『{f816}善意{f817}ぜんい{f818}』と『{f816}悪意{f817}あくい{f818}』が{f816}暴{f817}あば{f818}れ{f816}出{f817}だ{f818}し{f801}それに{f816}翻弄{f817}ほんろう{f818}される{f816}夢{f817}ゆめ{f818}だ{f801}{f802}…{f816}目覚{f817}めざ{f818}めさせてくれたのは {f816}貴様{f817}きさま{f818}か{f801}{ffff}</source>
    <target>{f812}マサカド{0000}{f813}{0100}{0000}{5099}{0700}…{f816}悪{f817}わる{f818}い{f816}夢{f817}ゆめ{f818}を{f816}見{f817}み{f818}ていた{f801}{f802}{f816}我{f817}わ{f818}が{f816}体内{f817}たいない{f818}の『{f816}善意{f817}ぜんい{f818}』と『{f816}悪意{f817}あくい{f818}』が{f816}暴{f817}あば{f818}れ{f816}出{f817}だ{f818}し{f801}それに{f816}翻弄{f817}ほんろう{f818}される{f816}夢{f817}ゆめ{f818}だ{f801}{f802}…{f816}目覚{f817}めざ{f818}めさせてくれたのは {f816}貴様{f817}きさま{f818}か{f801}{ffff}</target>
  </entry>
  <entry id="13">
    <source>マサカドは {f816}自我{f817}じが{f818}を{f816}取{f817}と{f818}り{f816}戻{f817}もど{f818}した{f801}{ffff}</source>
    <target>マサカドは {f816}自我{f817}じが{f818}を{f816}取{f817}と{f818}り{f816}戻{f817}もど{f818}した{f801}{ffff}</target>
  </entry>
  <entry id="14">
    <source>{f812}マサカド{0000}{f816}貴様{f817}きさま{f818}のうちに{f816}秘{f817}ひ{f818}めたる{f816}希望{f817}きぼう{f818}は{f801}{f816}我{f817}わ{f818}が{f816}自我{f817}じが{f818}となり しかと{f816}刻{f817}きざ{f818}み{f816}込{f817}こ{f818}まれた{f801}{f802}この{f816}自我{f817}じが{f818}…{f816}貴様{f817}きさま{f818}の{f816}希望{f817}きぼう{f818}と{f816}共{f817}とも{f818}に{f801}これより{f816}東京{f817}とうきょう{f818}を{f816}守護{f817}しゅご{f818}してゆこうぞ{f801}{ffff}</source>
    <target>{f812}マサカド{0000}{f816}貴様{f817}きさま{f818}のうちに{f816}秘{f817}ひ{f818}めたる{f816}希望{f817}きぼう{f818}は{f801}{f816}我{f817}わ{f818}が{f816}自我{f817}じが{f818}となり しかと{f816}刻{f817}きざ{f818}み{f816}込{f817}こ{f818}まれた{f801}{f802}この{f816}自我{f817}じが{f818}…{f816}貴様{f817}きさま{f818}の{f816}希望{f817}きぼう{f818}と{f816}共{f817}とも{f818}に{f801}これより{f816}東京{f817}とうきょう{f818}を{f816}守護{f817}しゅご{f818}してゆこうぞ{f801}{ffff}</target>
  </entry>
  <entry id="21">
    <source>{f816}大陸間弾道{f817}たいりくかんだんどう{f818}ミサイルが{f801}{f816}東京{f817}とうきょう{f818}に{f816}到達{f817}とうたつ{f818}した{f801}{f802}{f816}激{f817}はげ{f818}しい{f816}光{f817}ひかり{f818}が {f816}東京{f817}とうきょう{f818}を{f816}呑{f817}の{f818}みこんだ…{f801}{ffff}</source>
    <target>{f816}大陸間弾道{f817}たいりくかんだんどう{f818}ミサイルが{f801}{f816}東京{f817}とうきょう{f818}に{f816}到達{f817}とうたつ{f818}した{f801}{f802}{f816}激{f817}はげ{f818}しい{f816}光{f817}ひかり{f818}が {f816}東京{f817}とうきょう{f818}を{f816}呑{f817}の{f818}みこんだ…{f801}{ffff}</target>
  </entry>
  <entry id="1006">
    <source>{f812}バロウズ{0000}{f87a}{0200}{f813}{0100}{0000}{841a}{0600}{f843}{0000}{f816}様{f817}さま{f818}{f801}ミサイル{f816}到達{f817}とうたつ{f818}まで あと{f804}{0500}5ターン{f804}{0000}よ{f801}{f802}{f816}残{f817}のこ{f818}り{f816}時間{f817}じかん{f818}が{f816}半分{f817}はんぶん{f818}を{f816}切{f817}き{f818}ったわ{f801}{f816}気{f817}き{f818}をつけて{f801}{ffff}</source>
    <target>{f812}バロウズ{0000}{f87a}{0200}{f813}{0100}{0000}{841a}{0600}{f843}{0000}{f816}様{f817}さま{f818}{f801}ミサイル{f816}到達{f817}とうたつ{f818}まで あと{f804}{0500}5ターン{f804}{0000}よ{f801}{f802}{f816}残{f817}のこ{f818}り{f816}時間{f817}じかん{f818}が{f816}半分{f817}はんぶん{f818}を{f816}切{f817}き{f818}ったわ{f801}{f816}気{f817}き{f818}をつけて{f801}{ffff}</target>
  </entry>
  <entry id="1008">
    <source>{f812}バロウズ{0000}{f87a}{0200}{f813}{0100}{0000}{821a}{0600}ミサイル{f816}到達{f817}とうたつ{f818}まで あと{f804}{0500}3ターン{f804}{0000}{f801}{f802}…{f816}急{f817}いそ{f818}いだ{f816}方{f817}ほう{f818}が{f816}良{f817}よ{f818}さそうね{f801}{ffff}</source>
    <target>{f812}バロウズ{0000}{f87a}{0200}{f813}{0100}{0000}{821a}{0600}ミサイル{f816}到達{f817}とうたつ{f818}まで あと{f804}{0500}3ターン{f804}{0000}{f801}{f802}…{f816}急{f817}いそ{f818}いだ{f816}方{f817}ほう{f818}が{f816}良{f817}よ{f818}さそうね{f801}{ffff}</target>
  </entry>
  <entry id="1009">
    <source>{f812}バロウズ{0000}{f87a}{0200}{f813}{0100}{0000}{831a}{0600}ミサイル{f816}到達{f817}とうたつ{f818}まで あと{f804}{0500}2ターン{f804}{0000}{f801}{f802}{f816}諦{f817}あきら{f818}めないで まだ{f816}時間{f817}じかん{f818}はある{f801}{ffff}</source>
    <target>{f812}バロウズ{0000}{f87a}{0200}{f813}{0100}{0000}{831a}{0600}ミサイル{f816}到達{f817}とうたつ{f818}まで あと{f804}{0500}2ターン{f804}{0000}{f801}{f802}{f816}諦{f817}あきら{f818}めないで まだ{f816}時間{f817}じかん{f818}はある{f801}{ffff}</target>
  </entry>
  <entry id="1010">
    <source>{f812}バロウズ{0000}{f87a}{0200}{f813}{0100}{0000}{5aab}{0400}ミサイル{f816}到達{f817}とうたつ{f818}まで あと{f804}{0500}1ターン{f804}{0000}{f801}{f802}このターンがラストチャンス{f801}{f843}{0000}{f816}様{f817}さま{f818}を{f816}信{f817}しん{f818}じているわ…{f801}{ffff}</source>
    <target>{f812}バロウズ{0000}{f87a}{0200}{f813}{0100}{0000}{5aab}{0400}ミサイル{f816}到達{f817}とうたつ{f818}まで あと{f804}{0500}1ターン{f804}{0000}{f801}{f802}このターンがラストチャンス{f801}{f843}{0000}{f816}様{f817}さま{f818}を{f816}信{f817}しん{f818}じているわ…{f801}{ffff}</target>
  </entry>
</mbm>