<mbm>
  <entry id="0">
    <source>{f812}全身を覆う男{0000}{f87a}{6100}{f813}{0100}{0000}{0c27}{0600}キヨハルさんはね {f816}神{f817}かみ{f818}の{f816}御業{f817}みわざ{f818}の{f816}直後{f817}ちょくご{f818}に{f801}このシェルターで{f816}酷{f817}ひど{f818}いいじめにあったんだ{f801}{f802}あの{f816}人{f817}ひと{f818}が{f816}天使{f817}てんし{f818}と{f816}共{f817}とも{f818}に{f816}悪魔{f817}あくま{f818}を{f816}倒{f817}たお{f818}したことで{f801}{f816}神{f817}かみ{f818}を{f816}邪魔{f817}じゃま{f818}する{f816}者{f817}もの{f818}がいなくなり…{f801}{f802}{f816}神{f817}かみ{f818}の{f816}御業{f817}みわざ{f818}が{f816}実現{f817}じつげん{f818}してしまったわけだから…{f801}{f802}だから{f816}責任{f817}せきにん{f818}を{f816}感{f817}かん{f818}じたんだろうね{f801}{f816}人々{f817}ひとびと{f818}に{f816}冷笑{f817}れいしょう{f818}されながら『{f816}神{f817}かみ{f818}』に{f816}祈{f817}いの{f818}り{f816}続{f817}つづ{f818}けた{f801}{f802}{f816}君{f817}きみ{f818}らくらいの{f816}歳{f817}とし{f818}の{f816}頃{f817}ころ{f818}から そんな{f816}日々{f817}ひび{f818}だ{f801}…そりゃ あんな{f816}風{f817}ふう{f818}になっちまうよな{f801}{ffff}</source>
    <target>{f812}全身を覆う男{0000}{f87a}{6100}{f813}{0100}{0000}{0c27}{0600}キヨハルさんはね {f816}神{f817}かみ{f818}の{f816}御業{f817}みわざ{f818}の{f816}直後{f817}ちょくご{f818}に{f801}このシェルターで{f816}酷{f817}ひど{f818}いいじめにあったんだ{f801}{f802}あの{f816}人{f817}ひと{f818}が{f816}天使{f817}てんし{f818}と{f816}共{f817}とも{f818}に{f816}悪魔{f817}あくま{f818}を{f816}倒{f817}たお{f818}したことで{f801}{f816}神{f817}かみ{f818}を{f816}邪魔{f817}じゃま{f818}する{f816}者{f817}もの{f818}がいなくなり…{f801}{f802}{f816}神{f817}かみ{f818}の{f816}御業{f817}みわざ{f818}が{f816}実現{f817}じつげん{f818}してしまったわけだから…{f801}{f802}だから{f816}責任{f817}せきにん{f818}を{f816}感{f817}かん{f818}じたんだろうね{f801}{f816}人々{f817}ひとびと{f818}に{f816}冷笑{f817}れいしょう{f818}されながら『{f816}神{f817}かみ{f818}』に{f816}祈{f817}いの{f818}り{f816}続{f817}つづ{f818}けた{f801}{f802}{f816}君{f817}きみ{f818}らくらいの{f816}歳{f817}とし{f818}の{f816}頃{f817}ころ{f818}から そんな{f816}日々{f817}ひび{f818}だ{f801}…そりゃ あんな{f816}風{f817}ふう{f818}になっちまうよな{f801}{ffff}</target>
  </entry>
  <entry id="1">
    <source>{f812}全身を覆う男{0000}{f87a}{6100}{f813}{0100}{0000}{0227}{0600}『プルートが{f816}死{f817}し{f818}んだ』って{f801}キヨハルさんが{f816}皆{f817}みんな{f818}に{f816}教{f817}おし{f818}えてくれたんだ{f801}{f802}キヨハルさんだけが{f801}なんか{f816}直感{f817}ちょっかん{f818}でわかったらしいんだよ{f801}{f802}シェルターの{f816}中{f817}なか{f818}を{f816}駆{f817}か{f818}け{f816}回{f817}まわ{f818}るキヨハルさん{f801}…{f816}本当{f817}ほんとう{f818}に{f816}嬉{f817}うれ{f818}しそうだったな{f801}{ffff}</source>
    <target>{f812}全身を覆う男{0000}{f87a}{6100}{f813}{0100}{0000}{0227}{0600}『プルートが{f816}死{f817}し{f818}んだ』って{f801}キヨハルさんが{f816}皆{f817}みんな{f818}に{f816}教{f817}おし{f818}えてくれたんだ{f801}{f802}キヨハルさんだけが{f801}なんか{f816}直感{f817}ちょっかん{f818}でわかったらしいんだよ{f801}{f802}シェルターの{f816}中{f817}なか{f818}を{f816}駆{f817}か{f818}け{f816}回{f817}まわ{f818}るキヨハルさん{f801}…{f816}本当{f817}ほんとう{f818}に{f816}嬉{f817}うれ{f818}しそうだったな{f801}{ffff}</target>
  </entry>
  <entry id="2">
    <source>{f812}全身を覆う男{0000}{f87a}{6100}{f813}{0100}{0000}{0227}{0600}{f816}毎日毎日{f817}まいにちまいにち{f818} アキラさんとの{f816}会議{f817}かいぎ{f818}だ{f801}{f816}本当{f817}ほんとう{f818} 1{f816}日{f817}にち{f818}があっという{f816}間{f817}ま{f818}だよ…{f801}{f802}でも{f816}忙{f817}いそが{f818}しいけど {f816}前{f817}まえ{f818}に{f816}進{f817}すす{f818}んでいる{f816}感{f817}かん{f818}じ…{f801}それは{f816}悪{f817}わる{f818}くないかな{f801}{ffff}</source>
    <target>{f812}全身を覆う男{0000}{f87a}{6100}{f813}{0100}{0000}{0227}{0600}{f816}毎日毎日{f817}まいにちまいにち{f818} アキラさんとの{f816}会議{f817}かいぎ{f818}だ{f801}{f816}本当{f817}ほんとう{f818} 1{f816}日{f817}にち{f818}があっという{f816}間{f817}ま{f818}だよ…{f801}{f802}でも{f816}忙{f817}いそが{f818}しいけど {f816}前{f817}まえ{f818}に{f816}進{f817}すす{f818}んでいる{f816}感{f817}かん{f818}じ…{f801}それは{f816}悪{f817}わる{f818}くないかな{f801}{ffff}</target>
  </entry>
  <entry id="3">
    <source>{f812}覇気の無い男{0000}{f87a}{a200}{f813}{0100}{0000}{2a27}{0600}{f816}思{f817}おも{f818}い{f816}出{f817}だ{f818}すよ {f816}昔{f817}むかし{f818}…{f816}東京{f817}とうきょう{f818}にな{f801}{f816}悪魔{f817}あくま{f818}を{f816}崇拝{f817}すうはい{f818}する{f816}連中{f817}れんちゅう{f818}がいたんだよ{f801}{f802}{f816}神{f817}かみ{f818}がいないってことは{f816}身{f817}み{f818}に{f816}染{f817}し{f818}みてる{f801}{f816}今{f817}いま{f818}の{f816}俺{f817}おれ{f818}なら…{f816}奴{f817}やつ{f818}らの{f816}勧誘{f817}かんゆう{f818}に{f816}乗{f817}の{f818}っちまうな{f801}{ffff}</source>
    <target>{f812}覇気の無い男{0000}{f87a}{a200}{f813}{0100}{0000}{2a27}{0600}{f816}思{f817}おも{f818}い{f816}出{f817}だ{f818}すよ {f816}昔{f817}むかし{f818}…{f816}東京{f817}とうきょう{f818}にな{f801}{f816}悪魔{f817}あくま{f818}を{f816}崇拝{f817}すうはい{f818}する{f816}連中{f817}れんちゅう{f818}がいたんだよ{f801}{f802}{f816}神{f817}かみ{f818}がいないってことは{f816}身{f817}み{f818}に{f816}染{f817}し{f818}みてる{f801}{f816}今{f817}いま{f818}の{f816}俺{f817}おれ{f818}なら…{f816}奴{f817}やつ{f818}らの{f816}勧誘{f817}かんゆう{f818}に{f816}乗{f817}の{f818}っちまうな{f801}{ffff}</target>
  </entry>
  <entry id="4">
    <source>{f812}覇気の無い男{0000}{f87a}{a200}{f813}{0100}{0000}{2a27}{0600}…そうか プルートが{f816}死{f817}し{f818}んだか{f801}これで{f816}肩{f817}かた{f818}の{f816}荷{f817}に{f818}が{f816}1{f817}ひと{f818}つ{f816}減{f817}へ{f818}ったんだな…{f801}{f802}でもやらなきゃいけないことが{f816}山積{f817}やまづ{f818}みだ{f801}『{f816}神{f817}かみ{f818}』なんかに{f816}恨{f817}うら{f818}み{f816}言{f817}ごと{f818}を{f816}言{f817}い{f818}う{f816}暇{f817}ひま{f818}もねぇよ{f801}{ffff}</source>
    <target>{f812}覇気の無い男{0000}{f87a}{a200}{f813}{0100}{0000}{2a27}{0600}…そうか プルートが{f816}死{f817}し{f818}んだか{f801}これで{f816}肩{f817}かた{f818}の{f816}荷{f817}に{f818}が{f816}1{f817}ひと{f818}つ{f816}減{f817}へ{f818}ったんだな…{f801}{f802}でもやらなきゃいけないことが{f816}山積{f817}やまづ{f818}みだ{f801}『{f816}神{f817}かみ{f818}』なんかに{f816}恨{f817}うら{f818}み{f816}言{f817}ごと{f818}を{f816}言{f817}い{f818}う{f816}暇{f817}ひま{f818}もねぇよ{f801}{ffff}</target>
  </entry>
  <entry id="5">
    <source>{f812}覇気の無い男{0000}{f87a}{a200}{f813}{0100}{0000}{2a27}{0600}{f816}東{f817}ひがし{f818}のミカド{f816}国{f817}こく{f818}も{f816}大事{f817}だいじ{f818}だが{f801}{f816}戦{f817}たたか{f818}える{f816}奴{f817}やつ{f818}が{f816}増{f817}ふ{f818}えてくれないとな{f801}{f802}{f816}悪魔{f817}あくま{f818}が{f816}急{f817}きゅう{f818}に{f816}増{f817}ふ{f818}えだしたんだ{f801}まったく…『{f816}神{f817}かみ{f818}』に{f816}恨{f817}うら{f818}み{f816}言{f817}ごと{f818}を{f816}言{f817}い{f818}う{f816}暇{f817}ひま{f818}もねぇ{f801}{ffff}</source>
    <target>{f812}覇気の無い男{0000}{f87a}{a200}{f813}{0100}{0000}{2a27}{0600}{f816}東{f817}ひがし{f818}のミカド{f816}国{f817}こく{f818}も{f816}大事{f817}だいじ{f818}だが{f801}{f816}戦{f817}たたか{f818}える{f816}奴{f817}やつ{f818}が{f816}増{f817}ふ{f818}えてくれないとな{f801}{f802}{f816}悪魔{f817}あくま{f818}が{f816}急{f817}きゅう{f818}に{f816}増{f817}ふ{f818}えだしたんだ{f801}まったく…『{f816}神{f817}かみ{f818}』に{f816}恨{f817}うら{f818}み{f816}言{f817}ごと{f818}を{f816}言{f817}い{f818}う{f816}暇{f817}ひま{f818}もねぇ{f801}{ffff}</target>
  </entry>
  <entry id="6">
    <source>{f812}ハンターの女{0000}{f87a}{6400}{f813}{0100}{0000}{9f26}{0600}{f816}私{f817}わたし{f818}らが『プルート{f816}城{f817}じょう{f818}』って{f816}呼{f817}よ{f818}ぶ{f816}場所{f817}ばしょ{f818}は{f801}ここから{f816}南東{f817}なんとう{f818}…{f816}橋{f817}はし{f818}を{f816}渡{f817}わた{f818}っていった{f816}先{f817}さき{f818}よ{f801}{f802}トゲが{f816}生{f817}は{f818}えたドーム{f816}状{f817}じょう{f818}のモノが{f816}見{f817}み{f818}えるわ{f801}そこがプルート{f816}城{f817}じょう{f818}よ{f801}{ffff}</source>
    <target>{f812}ハンターの女{0000}{f87a}{6400}{f813}{0100}{0000}{9f26}{0600}{f816}私{f817}わたし{f818}らが『プルート{f816}城{f817}じょう{f818}』って{f816}呼{f817}よ{f818}ぶ{f816}場所{f817}ばしょ{f818}は{f801}ここから{f816}南東{f817}なんとう{f818}…{f816}橋{f817}はし{f818}を{f816}渡{f817}わた{f818}っていった{f816}先{f817}さき{f818}よ{f801}{f802}トゲが{f816}生{f817}は{f818}えたドーム{f816}状{f817}じょう{f818}のモノが{f816}見{f817}み{f818}えるわ{f801}そこがプルート{f816}城{f817}じょう{f818}よ{f801}{ffff}</target>
  </entry>
  <entry id="7">
    <source>{f812}ハンターの女{0000}{f87a}{6400}{f813}{0100}{0000}{9f26}{0600}プルートは{f816}死{f817}し{f818}んでも{f801}プルート{f816}城{f817}じょう{f818}はなくならないみたいね…{f801}{f802}なんだか まだ{f816}神{f817}かみ{f818}に{f816}見{f817}み{f818}られている{f816}気{f817}き{f818}がする{f801}{f816}結局{f817}けっきょく{f818} どこまでいっても{f816}私{f817}わたし{f818}たちは…?{f801}{ffff}</source>
    <target>{f812}ハンターの女{0000}{f87a}{6400}{f813}{0100}{0000}{9f26}{0600}プルートは{f816}死{f817}し{f818}んでも{f801}プルート{f816}城{f817}じょう{f818}はなくならないみたいね…{f801}{f802}なんだか まだ{f816}神{f817}かみ{f818}に{f816}見{f817}み{f818}られている{f816}気{f817}き{f818}がする{f801}{f816}結局{f817}けっきょく{f818} どこまでいっても{f816}私{f817}わたし{f818}たちは…?{f801}{ffff}</target>
  </entry>
  <entry id="8">
    <source>{f812}ハンターの女{0000}{f87a}{6400}{f813}{0100}{0000}{bd26}{0600}プルートは{f816}死{f817}し{f818}んでも{f801}プルート{f816}城{f817}じょう{f818}はなくならないわ…{f801}{f802}なんだか まだ{f816}神{f817}かみ{f818}に{f816}見{f817}み{f818}られている{f816}気{f817}き{f818}がする{f801}{f816}結局{f817}けっきょく{f818} どこまでいっても{f816}私{f817}わたし{f818}たちは…?{f801}{ffff}</source>
    <target>{f812}ハンターの女{0000}{f87a}{6400}{f813}{0100}{0000}{bd26}{0600}プルートは{f816}死{f817}し{f818}んでも{f801}プルート{f816}城{f817}じょう{f818}はなくならないわ…{f801}{f802}なんだか まだ{f816}神{f817}かみ{f818}に{f816}見{f817}み{f818}られている{f816}気{f817}き{f818}がする{f801}{f816}結局{f817}けっきょく{f818} どこまでいっても{f816}私{f817}わたし{f818}たちは…?{f801}{ffff}</target>
  </entry>
  <entry id="9">
    <source>{f812}アキラ{0000}{f87a}{5400}{f813}{0100}{0000}{c120}{0600}{f816}私{f817}わたし{f818}たちは {f816}自分{f817}じぶん{f818}に{f816}都合{f817}つごう{f818}のいい『{f816}神{f817}かみ{f818}』を{f801}{f816}勝手{f817}かって{f818}に{f816}思{f817}おも{f818}い{f816}描{f817}えが{f818}いていただけだったんだ{f801}{f802}だからプルートを{f816}倒{f817}たお{f818}すことは{f816}神{f817}かみ{f818}に{f816}逆{f817}さか{f818}らい{f801}…{f816}逆恨{f817}さかうら{f818}みをすることなのかもしれない{f801}{f802}でも{f816}考{f817}かんが{f818}えてみてくれ…{f816}腹{f817}はら{f818}が{f816}立{f817}た{f818}つじゃないか{f801}{f816}私{f817}わたし{f818}は…{f816}神{f817}かみ{f818}に{f816}一矢報{f817}いっしむく{f818}いてやりたいんだ{f801}{f802}{f816}魔王{f817}まおう{f818}プルートの{f816}件{f817}けん{f818} {f816}頼{f817}たの{f818}んだよ{f801}{f816}報酬{f817}ほうしゅう{f818}は このリモコンだ{f801}{ffff}</source>
    <target>{f812}アキラ{0000}{f87a}{5400}{f813}{0100}{0000}{c120}{0600}{f816}私{f817}わたし{f818}たちは {f816}自分{f817}じぶん{f818}に{f816}都合{f817}つごう{f818}のいい『{f816}神{f817}かみ{f818}』を{f801}{f816}勝手{f817}かって{f818}に{f816}思{f817}おも{f818}い{f816}描{f817}えが{f818}いていただけだったんだ{f801}{f802}だからプルートを{f816}倒{f817}たお{f818}すことは{f816}神{f817}かみ{f818}に{f816}逆{f817}さか{f818}らい{f801}…{f816}逆恨{f817}さかうら{f818}みをすることなのかもしれない{f801}{f802}でも{f816}考{f817}かんが{f818}えてみてくれ…{f816}腹{f817}はら{f818}が{f816}立{f817}た{f818}つじゃないか{f801}{f816}私{f817}わたし{f818}は…{f816}神{f817}かみ{f818}に{f816}一矢報{f817}いっしむく{f818}いてやりたいんだ{f801}{f802}{f816}魔王{f817}まおう{f818}プルートの{f816}件{f817}けん{f818} {f816}頼{f817}たの{f818}んだよ{f801}{f816}報酬{f817}ほうしゅう{f818}は このリモコンだ{f801}{ffff}</target>
  </entry>
  <entry id="10">
    <source>{f812}アキラ{0000}{f87a}{5400}{f813}{0100}{0000}{c120}{0600}…そう{f816}言{f817}い{f818}えば {f816}渋谷{f817}しぶや{f818}の{f816}人々{f817}ひとびと{f818}を{f801}{f816}解放{f817}かいほう{f818}してくれたそうだね{f801}{f802}{f816}無断{f817}むだん{f818}でターミナルを{f816}使{f817}つか{f818}ったのは{f801}あまり{f816}感心{f817}かんしん{f818}できないが…{f801}{f802}{f816}皆{f817}みんな{f818}の{f816}願{f817}ねが{f818}いを{f816}叶{f817}かな{f818}えてくれてありがとう{f801}{f816}心{f817}こころ{f818}から{f816}感謝{f817}かんしゃ{f818}するよ{f801}{ffff}</source>
    <target>{f812}アキラ{0000}{f87a}{5400}{f813}{0100}{0000}{c120}{0600}…そう{f816}言{f817}い{f818}えば {f816}渋谷{f817}しぶや{f818}の{f816}人々{f817}ひとびと{f818}を{f801}{f816}解放{f817}かいほう{f818}してくれたそうだね{f801}{f802}{f816}無断{f817}むだん{f818}でターミナルを{f816}使{f817}つか{f818}ったのは{f801}あまり{f816}感心{f817}かんしん{f818}できないが…{f801}{f802}{f816}皆{f817}みんな{f818}の{f816}願{f817}ねが{f818}いを{f816}叶{f817}かな{f818}えてくれてありがとう{f801}{f816}心{f817}こころ{f818}から{f816}感謝{f817}かんしゃ{f818}するよ{f801}{ffff}</target>
  </entry>
  <entry id="11">
    <source>{f812}気丈な女{0000}{f87a}{6200}{f813}{0100}{0000}{8527}{0600}…{f816}貴方{f817}あなた{f818}たち プルートを{f816}倒{f817}たお{f818}したのよね?{f801}だったらついでに{f816}商会{f817}しょうかい{f818}の{f816}仕事{f817}しごと{f818}を{f816}手伝{f817}てつだ{f818}ってよ{f801}{f802}{f816}東京{f817}とうきょう{f818}は こんな{f816}有{f817}あ{f818}り{f816}様{f817}さま{f818}だけどさ{f801}{f816}私{f817}わたし{f818}たちは{f816}生{f817}い{f818}きてるんだもの…{f801}{ffff}</source>
    <target>{f812}気丈な女{0000}{f87a}{6200}{f813}{0100}{0000}{8527}{0600}…{f816}貴方{f817}あなた{f818}たち プルートを{f816}倒{f817}たお{f818}したのよね?{f801}だったらついでに{f816}商会{f817}しょうかい{f818}の{f816}仕事{f817}しごと{f818}を{f816}手伝{f817}てつだ{f818}ってよ{f801}{f802}{f816}東京{f817}とうきょう{f818}は こんな{f816}有{f817}あ{f818}り{f816}様{f817}さま{f818}だけどさ{f801}{f816}私{f817}わたし{f818}たちは{f816}生{f817}い{f818}きてるんだもの…{f801}{ffff}</target>
  </entry>
  <entry id="12">
    <source>{f812}気丈な女{0000}{f87a}{6200}{f813}{0100}{0000}{8527}{0600}…{f816}貴方{f817}あなた{f818} {f816}戦闘{f817}せんとう{f818}の{f816}心得{f817}こころえ{f818}がありそうね{f801}だったら{f816}商会{f817}しょうかい{f818}の{f816}仕事{f817}しごと{f818}を{f816}手伝{f817}てつだ{f818}ってよ{f801}{f802}{f816}東京{f817}とうきょう{f818}は こんな{f816}有{f817}あ{f818}り{f816}様{f817}さま{f818}だけどさ{f801}{f816}私{f817}わたし{f818}たちは{f816}生{f817}い{f818}きてるんだもの…{f801}{ffff}</source>
    <target>{f812}気丈な女{0000}{f87a}{6200}{f813}{0100}{0000}{8527}{0600}…{f816}貴方{f817}あなた{f818} {f816}戦闘{f817}せんとう{f818}の{f816}心得{f817}こころえ{f818}がありそうね{f801}だったら{f816}商会{f817}しょうかい{f818}の{f816}仕事{f817}しごと{f818}を{f816}手伝{f817}てつだ{f818}ってよ{f801}{f802}{f816}東京{f817}とうきょう{f818}は こんな{f816}有{f817}あ{f818}り{f816}様{f817}さま{f818}だけどさ{f801}{f816}私{f817}わたし{f818}たちは{f816}生{f817}い{f818}きてるんだもの…{f801}{ffff}</target>
  </entry>
</mbm>